ai_cli/__init__.py
ai_cli/autocomplete.py
ai_cli/command_mapper.py
ai_cli/context_manager.py
ai_cli/executor.py
ai_cli/intent_parser.py
ai_cli/llm_generator.py
ai_cli/main.py
ai_cli/planner.py
ai_cli/safety.py
ai_cli/undo_manager.py
ai_cli_llm-2.0.3.dist-info/METADATA
ai_cli_llm-2.0.3.dist-info/WHEEL
ai_cli_llm-2.0.3.dist-info/entry_points.txt
ai_cli_llm-2.0.3.dist-info/top_level.txt
ai_cli_llm-2.0.3.dist-info/RECORD
