Metadata-Version: 2.4
Name: ai-cli-llm
Version: 2.0.3
Summary: AI-powered CLI assistant with Gemini LLM command generation and human confirmation
Author: Your Name
Requires-Python: >=3.10
Requires-Dist: google-generativeai>=0.3.0
Requires-Dist: requests>=2.28.0
Requires-Dist: python-dotenv>=0.19.0
Dynamic: author
Dynamic: description
Dynamic: description-content-type
Dynamic: requires-dist
Dynamic: requires-python
Dynamic: summary
